Classfile /home/haschisch/Projects/cl/test/Main.class
  Last modified 02.08.2021; size 888 bytes
  SHA-256 checksum cdeb683611ff28d59e07a453b71849d7f46c45a187a295d6da201996aea2655f
  Compiled from "Main.java"
class Main
  minor version: 0
  major version: 60
  flags: (0x0020) ACC_SUPER
  this_class: #8                          // Main
  super_class: #2                         // java/lang/Object
  interfaces: 0, fields: 2, methods: 8, attributes: 1
Constant pool:
   #1 = Methodref          #2.#3          // java/lang/Object."<init>":()V
   #2 = Class              #4             // java/lang/Object
   #3 = NameAndType        #5:#6          // "<init>":()V
   #4 = Utf8               java/lang/Object
   #5 = Utf8               <init>
   #6 = Utf8               ()V
   #7 = Fieldref           #8.#9          // Main.three:I
   #8 = Class              #10            // Main
   #9 = NameAndType        #11:#12        // three:I
  #10 = Utf8               Main
  #11 = Utf8               three
  #12 = Utf8               I
  #13 = Methodref          #8.#14         // Main.five:()I
  #14 = NameAndType        #15:#16        // five:()I
  #15 = Utf8               five
  #16 = Utf8               ()I
  #17 = Methodref          #8.#18         // Main.fac:(I)I
  #18 = NameAndType        #19:#20        // fac:(I)I
  #19 = Utf8               fac
  #20 = Utf8               (I)I
  #21 = Methodref          #8.#22         // Main.fib:(I)I
  #22 = NameAndType        #23:#20        // fib:(I)I
  #23 = Utf8               fib
  #24 = Methodref          #8.#25         // Main.two:()I
  #25 = NameAndType        #26:#16        // two:()I
  #26 = Utf8               two
  #27 = Methodref          #8.#3          // Main."<init>":()V
  #28 = Methodref          #8.#29         // Main.getThree:()I
  #29 = NameAndType        #30:#16        // getThree:()I
  #30 = Utf8               getThree
  #31 = Fieldref           #32.#33        // Two.TWO:I
  #32 = Class              #34            // Two
  #33 = NameAndType        #35:#12        // TWO:I
  #34 = Utf8               Two
  #35 = Utf8               TWO
  #36 = Fieldref           #8.#37         // Main.MyField:I
  #37 = NameAndType        #38:#12        // MyField:I
  #38 = Utf8               MyField
  #39 = Utf8               Code
  #40 = Utf8               LineNumberTable
  #41 = Utf8               main
  #42 = Utf8               ([Ljava/lang/String;)V
  #43 = Utf8               StackMapTable
  #44 = Utf8               <clinit>
  #45 = Utf8               SourceFile
  #46 = Utf8               Main.java
{
  public int three;
    descriptor: I
    flags: (0x0001) ACC_PUBLIC

  public static int MyField;
    descriptor: I
    flags: (0x0009) ACC_PUBLIC, ACC_STATIC

  public Main();
    descriptor: ()V
    flags: (0x0001) ACC_PUBLIC
    Code:
      stack=2, locals=1, args_size=1
         0: aload_0
         1: invokespecial #1                  // Method java/lang/Object."<init>":()V
         4: aload_0
         5: iconst_3
         6: putfield      #7                  // Field three:I
         9: return
      LineNumberTable:
        line 4: 0
        line 5: 4
        line 6: 9

  public static void main(java.lang.String[]);
    descriptor: ([Ljava/lang/String;)V
    flags: (0x0009) ACC_PUBLIC, ACC_STATIC
    Code:
      stack=2, locals=2, args_size=1
         0: invokestatic  #13                 // Method five:()I
         3: pop
         4: iconst_5
         5: invokestatic  #17                 // Method fac:(I)I
         8: pop
         9: iconst_5
        10: invokestatic  #21                 // Method fib:(I)I
        13: pop
        14: invokestatic  #24                 // Method two:()I
        17: pop
        18: new           #8                  // class Main
        21: dup
        22: invokespecial #27                 // Method "<init>":()V
        25: astore_1
        26: aload_1
        27: invokevirtual #28                 // Method getThree:()I
        30: pop
        31: return
      LineNumberTable:
        line 11: 0
        line 12: 4
        line 13: 9
        line 14: 14
        line 16: 18
        line 17: 26
        line 18: 31

  public static int two();
    descriptor: ()I
    flags: (0x0009) ACC_PUBLIC, ACC_STATIC
    Code:
      stack=1, locals=0, args_size=0
         0: getstatic     #31                 // Field Two.TWO:I
         3: ireturn
      LineNumberTable:
        line 21: 0

  public static int fac(int);
    descriptor: (I)I
    flags: (0x0009) ACC_PUBLIC, ACC_STATIC
    Code:
      stack=2, locals=3, args_size=1
         0: iload_0
         1: ifne          6
         4: iconst_0
         5: ireturn
         6: iconst_1
         7: istore_1
         8: iconst_2
         9: istore_2
        10: iload_2
        11: iload_0
        12: if_icmpgt     25
        15: iload_1
        16: iload_2
        17: imul
        18: istore_1
        19: iinc          2, 1
        22: goto          10
        25: iload_1
        26: ireturn
      LineNumberTable:
        line 25: 0
        line 27: 6
        line 28: 8
        line 29: 15
        line 28: 19
        line 31: 25
      StackMapTable: number_of_entries = 3
        frame_type = 6 /* same */
        frame_type = 253 /* append */
          offset_delta = 3
          locals = [ int, int ]
        frame_type = 250 /* chop */
          offset_delta = 14

  public static int five();
    descriptor: ()I
    flags: (0x0009) ACC_PUBLIC, ACC_STATIC
    Code:
      stack=1, locals=0, args_size=0
         0: getstatic     #36                 // Field MyField:I
         3: ireturn
      LineNumberTable:
        line 35: 0

  public int getThree();
    descriptor: ()I
    flags: (0x0001) ACC_PUBLIC
    Code:
      stack=1, locals=1, args_size=1
         0: aload_0
         1: getfield      #7                  // Field three:I
         4: ireturn
      LineNumberTable:
        line 39: 0

  public static int fib(int);
    descriptor: (I)I
    flags: (0x0009) ACC_PUBLIC, ACC_STATIC
    Code:
      stack=3, locals=1, args_size=1
         0: iload_0
         1: ifeq          9
         4: iload_0
         5: iconst_1
         6: if_icmpne     11
         9: iconst_1
        10: ireturn
        11: iload_0
        12: iconst_1
        13: isub
        14: invokestatic  #21                 // Method fib:(I)I
        17: iload_0
        18: iconst_2
        19: isub
        20: invokestatic  #21                 // Method fib:(I)I
        23: iadd
        24: ireturn
      LineNumberTable:
        line 43: 0
        line 44: 9
        line 46: 11
      StackMapTable: number_of_entries = 2
        frame_type = 9 /* same */
        frame_type = 1 /* same */

  static {};
    descriptor: ()V
    flags: (0x0008) ACC_STATIC
    Code:
      stack=1, locals=0, args_size=0
         0: iconst_5
         1: putstatic     #36                 // Field MyField:I
         4: return
      LineNumberTable:
        line 8: 0
}
SourceFile: "Main.java"
